langbear/__init__.py
langbear-0.0.1.dist-info/METADATA
langbear-0.0.1.dist-info/WHEEL
langbear-0.0.1.dist-info/licenses/LICENSE
langbear-0.0.1.dist-info/RECORD
