Metadata-Version: 2.1
Name: langbear
Version: 0.0.1
Summary: AI prompt management platform.
Project-URL: Homepage, https://langbear.runbear.io
Project-URL: Bug Tracker, https://github.com/runbear-io/langbear-python/issues
Author-email: Runbear <contact@runbear.io>
License-File: LICENSE
Classifier: License :: OSI Approved :: MIT License
Classifier: Operating System :: OS Independent
Classifier: Programming Language :: Python :: 3
Requires-Python: >=3.7
